    <shared>
        <application/>
        <application-group/>
        <service/>
        <service-group/>
        <botnet>
            <configuration>
                <http>
                    <dynamic-dns>
                        <enabled>yes</enabled>
                        <threshold>5</threshold>
                    </dynamic-dns>
                    <malware-sites>
                        <enabled>yes</enabled>
                        <threshold>5</threshold>
                    </malware-sites>
                    <recent-domains>
                        <enabled>yes</enabled>
                        <threshold>5</threshold>
                    </recent-domains>
                    <ip-domains>
                        <enabled>yes</enabled>
                        <threshold>10</threshold>
                    </ip-domains>
                    <executables-from-unknown-sites>
                        <enabled>yes</enabled>
                        <threshold>5</threshold>
                    </executables-from-unknown-sites>
                </http>
                <other-applications>
                    <irc>yes</irc>
                </other-applications>
                <unknown-applications>
                    <unknown-tcp>
                        <destinations-per-hour>10</destinations-per-hour>
                        <sessions-per-hour>10</sessions-per-hour>
                        <session-length>
                            <maximum-bytes>100</maximum-bytes>
                            <minimum-bytes>50</minimum-bytes>
                        </session-length>
                    </unknown-tcp>
                    <unknown-udp>
                        <destinations-per-hour>10</destinations-per-hour>
                        <sessions-per-hour>10</sessions-per-hour>
                        <session-length>
                            <maximum-bytes>100</maximum-bytes>
                            <minimum-bytes>50</minimum-bytes>
                        </session-length>
                    </unknown-udp>
                </unknown-applications>
            </configuration>
            <report>
                <topn>100</topn>
                <scheduled>yes</scheduled>
            </report>
        </botnet>
    </shared>
